agentix_core/__init__.py
agentix_core/v1/__init__.py
agentix_core/v1/agent_task_queue_worker.py
agentix_core/v1/agentix_logger.py
agentix_core/v1/core.py
agentix_core/v1/system_events.py
agentix_core/v1/utils.py
agentix_core/v1/vault.py
agentix_core-1.0.1.dist-info/licenses/LICENSE
agentix_core-1.0.1.dist-info/METADATA
agentix_core-1.0.1.dist-info/WHEEL
agentix_core-1.0.1.dist-info/top_level.txt
agentix_core-1.0.1.dist-info/RECORD
