Metadata-Version: 2.4
Name: agentix-core
Version: 1.0.1
Summary: Core module for the Agentix platform
License-Expression: Apache-2.0
Project-URL: Homepage, https://github.com/FIDOX/py-plugin-agentix-core
Project-URL: Bug Tracker, https://github.com/FIDOX/py-plugin-agentix-core/issues
Requires-Python: >=3.8
License-File: LICENSE
Requires-Dist: aiohttp>=3.8.0
Requires-Dist: aio_pika>=9.4.0
Requires-Dist: PyJWT>=2.0.0
Requires-Dist: infisicalsdk>=1.0.3
Dynamic: license-file
